sanstyle/__init__.py
sanstyle/utils.py
sanstyle/display/__init__.py
sanstyle/display/_html.py
sanstyle/display/html.py
sanstyle/display/template.py
sanstyle/github/__init__.py
sanstyle/github/file.py
sanstyle-0.2.2.dist-info/LICENSE
sanstyle-0.2.2.dist-info/METADATA
sanstyle-0.2.2.dist-info/WHEEL
sanstyle-0.2.2.dist-info/top_level.txt
sanstyle-0.2.2.dist-info/RECORD
