Metadata-Version: 2.1
Name: sanstyle
Version: 0.2.2
Summary: Dash App
Home-page: https://github.com/xinetzone/sanstyle
Author: xinetzone
Author-email: xinzone@outlook.com
License: UNKNOWN
Platform: UNKNOWN
Classifier: Programming Language :: Python :: 3
Classifier: Development Status :: 2 - Pre-Alpha
Classifier: Operating System :: Microsoft :: Windows :: Windows 10
Classifier: Operating System :: POSIX :: Linux
Requires-Python: >=3.8
License-File: LICENSE
